CLIGIF/__init__.py
CLIGIF/assign_form.py
CLIGIF/converter.py
CLIGIF/display.py
CLIGIF/main.py
CLIGIF-1.0.dist-info/METADATA
CLIGIF-1.0.dist-info/WHEEL
CLIGIF-1.0.dist-info/top_level.txt
CLIGIF-1.0.dist-info/RECORD
