Metadata-Version: 2.1
Name: CLIGIF
Version: 1.0
Requires-Dist: Pillow (>=9.0.0)
